<annotation>
	<folder>train</folder>
	<filename>X-90-0.png</filename>
	<path /><source>
		<database>Unknown</database>
	</source>
	<size>
		<width>512</width>
		<height>512</height>
		<depth>3</depth>
	</size>
	<segmented>0</segmented>
	<object>
		<name>weed</name>
		<pose>Unspecified</pose>
		<truncated>0</truncated>
		<difficult>0</difficult>
		<bndbox>
			<xmin>121</xmin>
			<ymin>88</ymin>
			<xmax>157</xmax>
			<ymax>123</ymax>
		</bndbox>
	</object>
	<object>
		<name>sugarbeet</name>
		<pose>Unspecified</pose>
		<truncated>0</truncated>
		<difficult>0</difficult>
		<bndbox>
			<xmin>78</xmin>
			<ymin>198</ymin>
			<xmax>176</xmax>
			<ymax>288</ymax>
		</bndbox>
	</object>
	<object>
		<name>sugarbeet</name>
		<pose>Unspecified</pose>
		<truncated>0</truncated>
		<difficult>0</difficult>
		<bndbox>
			<xmin>200</xmin>
			<ymin>132</ymin>
			<xmax>338</xmax>
			<ymax>306</ymax>
		</bndbox>
	</object>
	<object>
		<name>sugarbeet</name>
		<pose>Unspecified</pose>
		<truncated>1</truncated>
		<difficult>0</difficult>
		<bndbox>
			<xmin>423</xmin>
			<ymin>145</ymin>
			<xmax>512</xmax>
			<ymax>306</ymax>
		</bndbox>
	</object>
</annotation>