<annotation>
	<folder>train</folder>
	<filename>X3-100-1.png</filename>
	<path /><source>
		<database>Unknown</database>
	</source>
	<size>
		<width>512</width>
		<height>512</height>
		<depth>3</depth>
	</size>
	<segmented>0</segmented>
	<object>
		<name>sugarbeet</name>
		<pose>Unspecified</pose>
		<truncated>1</truncated>
		<difficult>0</difficult>
		<bndbox>
			<xmin>1</xmin>
			<ymin>41</ymin>
			<xmax>108</xmax>
			<ymax>167</ymax>
		</bndbox>
	</object>
	<object>
		<name>sugarbeet</name>
		<pose>Unspecified</pose>
		<truncated>0</truncated>
		<difficult>0</difficult>
		<bndbox>
			<xmin>81</xmin>
			<ymin>23</ymin>
			<xmax>234</xmax>
			<ymax>146</ymax>
		</bndbox>
	</object>
	<object>
		<name>sugarbeet</name>
		<pose>Unspecified</pose>
		<truncated>1</truncated>
		<difficult>0</difficult>
		<bndbox>
			<xmin>402</xmin>
			<ymin>1</ymin>
			<xmax>512</xmax>
			<ymax>153</ymax>
		</bndbox>
	</object>
	<object>
		<name>sugarbeet</name>
		<pose>Unspecified</pose>
		<truncated>0</truncated>
		<difficult>0</difficult>
		<bndbox>
			<xmin>335</xmin>
			<ymin>332</ymin>
			<xmax>509</xmax>
			<ymax>503</ymax>
		</bndbox>
	</object>
	<object>
		<name>sugarbeet</name>
		<pose>Unspecified</pose>
		<truncated>0</truncated>
		<difficult>0</difficult>
		<bndbox>
			<xmin>209</xmin>
			<ymin>348</ymin>
			<xmax>348</xmax>
			<ymax>497</ymax>
		</bndbox>
	</object>
	<object>
		<name>sugarbeet</name>
		<pose>Unspecified</pose>
		<truncated>0</truncated>
		<difficult>0</difficult>
		<bndbox>
			<xmin>78</xmin>
			<ymin>344</ymin>
			<xmax>239</xmax>
			<ymax>458</ymax>
		</bndbox>
	</object>
</annotation>